ecmwf/jupyter_components/__init__.py
ecmwf/jupyter_components/jupyter_forms.py
ecmwf/jupyter_components/version.py
ecmwf_jupyter_components-0.1.1.dist-info/licenses/LICENSE
ecmwf_jupyter_components-0.1.1.dist-info/METADATA
ecmwf_jupyter_components-0.1.1.dist-info/WHEEL
ecmwf_jupyter_components-0.1.1.dist-info/top_level.txt
ecmwf_jupyter_components-0.1.1.dist-info/RECORD
