Metadata-Version: 2.4
Name: ecmwf-jupyter-components
Version: 0.1.1
Summary: Components for working in Jupyter Environments
License:                                  Apache License
Classifier: Development Status :: 2 - Pre-Alpha
Classifier: Intended Audience :: Science/Research
Classifier: License :: OSI Approved :: Apache Software License
Classifier: Operating System :: OS Independent
Classifier: Programming Language :: Python
Classifier: Programming Language :: Python :: 3
Classifier: Programming Language :: Python :: 3.11
Classifier: Topic :: Scientific/Engineering
License-File: LICENSE
Requires-Dist: ecmwf-datastores-client
Requires-Dist: ipywidgets
Dynamic: license-file
